MANIFEST.in
README.rst
setup.py
castctrl/__init__.py
castctrl/__main__.py
castctrl/castctrl.py
castctrl.egg-info/PKG-INFO
castctrl.egg-info/SOURCES.txt
castctrl.egg-info/dependency_links.txt
castctrl.egg-info/entry_points.txt
castctrl.egg-info/requires.txt
castctrl.egg-info/top_level.txt